[{"Titulo": "Mecánico Industrial (1 vacantes)", "Ocupacion": "Mecanicos y mecanicas de maquinas agricolas e industriales", "Vacantes": 1, "Empresa": "Pineal", "Actividad económica": "Actividades de consultoría de gestión", "Ubicacion": "Metropolitana, Quilicura", "Fecha": "19/08/2020", "Salario": "Reservado", "Tipo": "Jornada Completa", "Nivel educacional": "Educación media completa", "Experiencia": "5 años", "Tipo educación media": "Educación Técnico Profesional", "Educación Científico Humanista": "Tipo de contrato:", "Contrato a plazo Fijo": "Nivel de Cargo ofrecido:", "Operario": "Oferta de tipo práctica profesional:", "Oferta de tipo práctica profesional": "No"}, {"Titulo": "Operarios de bodega, Lampa (5 vacantes)", "Ocupacion": "Empleados y empleadas de control de abastecimientos e inventario - Empleados y empleadas de servicios de apoyo a la produccion", "Vacantes": 5, "Empresa": "Xinergia Laboral Servicios Generales", "Actividad económica": "Otras actividades de servicios de apoyo a las empresas n.c.p.", "Ubicacion": "Metropolitana, Lampa", "Fecha": "19/08/2020", "Salario": "Reservado", "Tipo": "Sin limitación horaria", "Nivel educacional": "Educación media completa", "Experiencia": "1 años", "Tipo educación media": "Educación Científico Humanista", "Tipo de contrato": "Contrato a plazo Fijo", "Nivel de Cargo ofrecido": "Operario", "Turnos de trabajo": "Oferta de tipo práctica profesional:", "Oferta de tipo práctica profesional": "No"}, {"Titulo": "INGENIERO MEDIO AMBIENTE (1 vacantes)", "Ocupacion": "Ingenieros medioambientales", "Vacantes": 1, "Empresa": "Confidencial", "Actividad económica": "Explotación de otras minas y canteras n.c.p.", "Ubicacion": "Atacama, Copiapó", "Fecha": "19/08/2020", "Salario": "Reservado", "Tipo": "Jornada Completa", "Nivel educacional": "", "Experiencia": "3 años", "Tipo de contrato": "Contrato por obra o faena", "Nivel de Cargo ofrecido": "Otro", "Oferta de tipo práctica profesional": "No"}, {"Titulo": "PREVENCIONISTA DE RIESGOS (2 vacantes)", "Ocupacion": "Prevencionista de riesgo", "Vacantes": 2, "Empresa": "Confidencial", "Actividad económica": "Explotación de otras minas y canteras n.c.p.", "Ubicacion": "Atacama, Chañaral", "Fecha": "19/08/2020", "Salario": "Reservado", "Tipo": "Jornada Completa", "Nivel educacional": "", "Experiencia": "3 años", "Tipo de contrato": "Contrato por obra o faena", "Nivel de Cargo ofrecido": "Otro", "Oferta de tipo práctica profesional": "No"}, {"Titulo": "OPERADOR GRUA HORQUILLA CASABLANCA (10 vacantes)", "Ocupacion": "Operarios y operarias de maquinaria agricola y forestal motorizada - Operarios y operarias de maquinas de movimiento de tierras y afines", "Vacantes": 10, "Empresa": "Manpower Servicios Integrales", "Actividad económica": "Otras actividades de servicios personales n.c.p.", "Descripción de la Empresa": "SERVICIO DE RECURSOS HUMANOS.", "Ubicacion": "Valparaíso, Casablanca", "Fecha": "19/08/2020", "Salario": "301.000\n - \n450.000", "Tipo": "Jornada Completa", "Nivel educacional": "", "Experiencia": "1 años", "Tipo de contrato": "Contrato a plazo Fijo", "Nivel de Cargo ofrecido": "Operario", "Oferta de tipo práctica profesional": "No"}, {"Titulo": "MOTORISTA DE COMIDA RÁPIDA - OMIL LAMPA (2 vacantes)", "Ocupacion": "Conductores y conductoras de automoviles taxis, camionetas y motocicletas", "Vacantes": 2, "Empresa": "ADMINISTRADORA DE FRANQUICIAS RENACIMIENTO SPA", "Actividad económica": "Otra", "Ubicacion": "Metropolitana, Lampa", "Fecha": "19/08/2020", "Salario": "Menora$301.000", "Tipo": "Jornada Parcial/part time", "Nivel educacional": "Educación media completa", "Experiencia": "1 años", "Tipo educación media": "Educación Científico Humanista", "Tipo de contrato": "Contrato a plazo Fijo", "Nivel de Cargo ofrecido": "Otro", "Oferta de tipo práctica profesional": "No"}, {"Titulo": "Operador de Grúa - OMIL LAMPA (5 vacantes)", "Ocupacion": "Operarios y operarias de gruas de aparatos elevadores y afines", "Vacantes": 5, "Empresa": "MEGALOGISTCA", "Actividad económica": "Otras actividades de servicios de apoyo a las empresas n.c.p.", "Ubicacion": "Metropolitana, Lampa", "Fecha": "19/08/2020", "Salario": "301.000\n - \n450.000", "Tipo": "Jornada Completa", "Nivel educacional": "Educación media completa", "Experiencia": "2 años", "Tipo educación media": "Educación Científico Humanista", "Licencias de conducir": "CLASE D - Maquinaria automotriz: tractores, palas mecánicas y otros.", "Tipo de contrato": "Contrato a plazo Fijo", "Nivel de Cargo ofrecido": "Otro", "Oferta de tipo práctica profesional": "No"}, {"Titulo": "Auxiliar de Aseo - OMIL LAMPA (1 vacantes)", "Ocupacion": "Limpiadores y limpiadoras de establecimientos", "Vacantes": 1, "Empresa": "Heavy Duty S.A.", "Actividad económica": "Venta al por mayor de otros tipos de maquinaria y equipo n.c.p.", "Ubicacion": "Metropolitana, Lampa", "Fecha": "19/08/2020", "Salario": "301.000\n - \n450.000", "Tipo": "Jornada Completa", "Nivel educacional": "Educación media completa", "Experiencia": "3 años", "Tipo educación media": "Educación Científico Humanista", "Tipo de contrato": "Contrato a plazo Fijo", "Nivel de Cargo ofrecido": "Otro", "Oferta de tipo práctica profesional": "No"}, {"Titulo": "Administrativo - Región Metropolitana (2 vacantes)", "Ocupacion": "Profesionales de nivel medio de servicios administrativos y afines - Secretarios administrativos", "Vacantes": 2, "Empresa": "Fundacion Arando Esperanza", "Actividad económica": "Otras actividades profesionales, científicas y técnicas n.c.p.", "Ubicacion": "Metropolitana, Santiago", "Fecha": "19/08/2020", "Salario": "301.000\n - \n450.000", "Tipo": "Jornada Parcial/part time", "Nivel educacional": "Educación media completa", "Experiencia": "1 años", "Tipo educación media": "Educación Técnico Profesional", "Tipo de contrato": "Contrato indefinido", "Nivel de Cargo ofrecido": "Administrativo", "Turnos de trabajo": "Solo mañanas", "Solo tarde": "Grupos de Empleo:", "Oferta de tipo práctica profesional": "No"}, {"Titulo": "Administrativo - IV Región (2 vacantes)", "Ocupacion": "Profesionales de nivel medio de servicios administrativos y afines - Secretarios administrativos", "Vacantes": 2, "Empresa": "Fundacion Arando Esperanza", "Actividad económica": "Otras actividades profesionales, científicas y técnicas n.c.p.", "Ubicacion": "Coquimbo, La Serena", "Fecha": "19/08/2020", "Salario": "301.000\n - \n450.000", "Tipo": "Jornada Parcial/part time", "Nivel educacional": "Educación media completa", "Experiencia": "1 años", "Tipo educación media": "Educación Técnico Profesional", "Tipo de contrato": "Contrato indefinido", "Nivel de Cargo ofrecido": "Administrativo", "Turnos de trabajo": "Solo mañanas", "Solo tarde": "Grupos de Empleo:", "Oferta de tipo práctica profesional": "No"}, {"Titulo": "Administrativo - VII Región (3 vacantes)", "Ocupacion": "Profesionales de nivel medio de servicios administrativos y afines - Secretarios administrativos", "Vacantes": 3, "Empresa": "Fundacion Arando Esperanza", "Actividad económica": "Otras actividades profesionales, científicas y técnicas n.c.p.", "Ubicacion": "Maule, Curicó", "Fecha": "19/08/2020", "Salario": "301.000\n - \n450.000", "Tipo": "Jornada Parcial/part time", "Nivel educacional": "Educación media completa", "Experiencia": "1 años", "Tipo educación media": "Educación Técnico Profesional", "Tipo de contrato": "Contrato indefinido", "Nivel de Cargo ofrecido": "Administrativo", "Turnos de trabajo": "Solo mañanas", "Solo tarde": "Grupos de Empleo:", "Oferta de tipo práctica profesional": "No"}, {"Titulo": "Operador de bodega y chofer (1 vacantes)", "Ocupacion": "Conductores y conductoras de camiones pesados - Otras ocupaciones", "Vacantes": 1, "Empresa": "Confidencial", "Actividad económica": "Venta al por menor de artículos de ferretería y materiales de construcción", "Descripción de la Empresa": "Empresa fundada en mayo del 2001 como barraca de fierro  se encuentra  ubicada en san bernardo dedicada a la importación , ventas por menor,distribución de productos de acero estructurales ,principalmente para la construcción,obras civiles,minería e industria.", "Ubicacion": "Metropolitana, San Bernardo", "Fecha": "19/08/2020", "Salario": "Reservado", "Tipo": "Jornada Completa", "Nivel educacional": "Educación media completa", "Experiencia": "1 años", "Tipo educación media": "Educación Técnico Profesional", "Licencias de conducir": "CLASE A4 - Transporte de carga cuyo peso bruto sea superior a 3.500 kilogramos.", "Tipo de contrato": "Contrato a plazo Fijo", "Nivel de Cargo ofrecido": "Operario", "Oferta de tipo práctica profesional": "No"}, {"Titulo": "Administrativo - XVI Región (1 vacantes)", "Ocupacion": "Profesionales de nivel medio de servicios administrativos y afines - Secretarios administrativos", "Vacantes": 1, "Empresa": "Fundacion Arando Esperanza", "Actividad económica": "Otras actividades profesionales, científicas y técnicas n.c.p.", "Ubicacion": "Ñuble, Chillán", "Fecha": "19/08/2020", "Salario": "301.000\n - \n450.000", "Tipo": "Jornada Parcial/part time", "Nivel educacional": "Educación media completa", "Experiencia": "1 años", "Tipo educación media": "Educación Técnico Profesional", "Tipo de contrato": "Contrato indefinido", "Nivel de Cargo ofrecido": "Administrativo", "Turnos de trabajo": "Solo mañanas", "Solo tarde": "Grupos de Empleo:", "Oferta de tipo práctica profesional": "No"}, {"Titulo": "Administrativo - VIII Región (1 vacantes)", "Ocupacion": "Profesionales de nivel medio de servicios administrativos y afines - Secretarios administrativos", "Vacantes": 1, "Empresa": "Fundacion Arando Esperanza", "Actividad económica": "Otras actividades profesionales, científicas y técnicas n.c.p.", "Ubicacion": "Bío Bío, Los Angeles", "Fecha": "19/08/2020", "Salario": "301.000\n - \n450.000", "Tipo": "Jornada Parcial/part time", "Nivel educacional": "Educación media completa", "Experiencia": "1 años", "Tipo educación media": "Educación Técnico Profesional", "Tipo de contrato": "Contrato indefinido", "Nivel de Cargo ofrecido": "Administrativo", "Turnos de trabajo": "Solo mañanas", "Solo tarde": "Grupos de Empleo:", "Oferta de tipo práctica profesional": "No"}, {"Titulo": "Administrativo - I Región (1 vacantes)", "Ocupacion": "Profesionales de nivel medio de servicios administrativos y afines - Secretarios administrativos", "Vacantes": 1, "Empresa": "Fundacion Arando Esperanza", "Actividad económica": "Otras actividades profesionales, científicas y técnicas n.c.p.", "Ubicacion": "Tarapacá, Iquique", "Fecha": "19/08/2020", "Salario": "301.000\n - \n450.000", "Tipo": "Jornada Parcial/part time", "Nivel educacional": "Educación media completa", "Experiencia": "1 años", "Tipo educación media": "Educación Técnico Profesional", "Tipo de contrato": "Contrato indefinido", "Nivel de Cargo ofrecido": "Administrativo", "Turnos de trabajo": "Solo mañanas", "Solo tarde": "Grupos de Empleo:", "Oferta de tipo práctica profesional": "No"}, {"Titulo": "Administrativo - II Región (1 vacantes)", "Ocupacion": "Profesionales de nivel medio de servicios administrativos y afines - Secretarios administrativos", "Vacantes": 1, "Empresa": "Fundacion Arando Esperanza", "Actividad económica": "Otras actividades profesionales, científicas y técnicas n.c.p.", "Ubicacion": "Antofagasta, Antofagasta", "Fecha": "19/08/2020", "Salario": "301.000\n - \n450.000", "Tipo": "Jornada Parcial/part time", "Nivel educacional": "Educación media completa", "Experiencia": "1 años", "Tipo educación media": "Educación Técnico Profesional", "Tipo de contrato": "Contrato indefinido", "Nivel de Cargo ofrecido": "Administrativo", "Turnos de trabajo": "Solo mañanas", "Solo tarde": "Grupos de Empleo:", "Oferta de tipo práctica profesional": "No"}, {"Titulo": "Operario de producción - Región Metropolitana (2 vacantes)", "Ocupacion": "Empleados y empleadas de servicios de apoyo a la produccion - Productores y trabajadores agropecuarios calificados cuya produccion se destina al mercado", "Vacantes": 2, "Empresa": "Fundacion Arando Esperanza", "Actividad económica": "Otras actividades profesionales, científicas y técnicas n.c.p.", "Ubicacion": "Metropolitana, Santiago", "Fecha": "19/08/2020", "Salario": "301.000\n - \n450.000", "Tipo": "Jornada Parcial/part time", "Nivel educacional": "", "Experiencia": "1 años", "Tipo de contrato": "Contrato indefinido", "Nivel de Cargo ofrecido": "Operario", "Turnos de trabajo": "Solo mañanas", "Solo tarde": "Grupos de Empleo:", "Oferta de tipo práctica profesional": "No"}, {"Titulo": "Operario de producción - X Región (2 vacantes)", "Ocupacion": "Empleados y empleadas de servicios de apoyo a la produccion - Productores y trabajadores agropecuarios calificados cuya produccion se destina al mercado", "Vacantes": 2, "Empresa": "Fundacion Arando Esperanza", "Actividad económica": "Otras actividades profesionales, científicas y técnicas n.c.p.", "Ubicacion": "Los Lagos, Puerto Montt", "Fecha": "19/08/2020", "Salario": "301.000\n - \n450.000", "Tipo": "Jornada Parcial/part time", "Nivel educacional": "", "Experiencia": "1 años", "Tipo de contrato": "Contrato indefinido", "Nivel de Cargo ofrecido": "Operario", "Turnos de trabajo": "Solo mañanas", "Solo tarde": "Grupos de Empleo:", "Oferta de tipo práctica profesional": "No"}, {"Titulo": "Operario de producción - IV Región (2 vacantes)", "Ocupacion": "Empleados y empleadas de servicios de apoyo a la produccion - Productores y trabajadores agropecuarios calificados cuya produccion se destina al mercado", "Vacantes": 2, "Empresa": "Fundacion Arando Esperanza", "Actividad económica": "Otras actividades profesionales, científicas y técnicas n.c.p.", "Ubicacion": "Coquimbo, La Serena", "Fecha": "19/08/2020", "Salario": "301.000\n - \n450.000", "Tipo": "Jornada Parcial/part time", "Nivel educacional": "", "Experiencia": "1 años", "Tipo de contrato": "Contrato indefinido", "Nivel de Cargo ofrecido": "Operario", "Turnos de trabajo": "Solo mañanas", "Solo tarde": "Grupos de Empleo:", "Oferta de tipo práctica profesional": "No"}, {"Titulo": "CAMPERO DE FUNDO  (1 vacantes)", "Ocupacion": "Criadores y criadoras de ganado y otros animales domésticos y productores de leche y sus derivados - Agricultores y agricultoras, trabajadores y trabajadoras calificadas de cultivos extensivos", "Vacantes": 1, "Empresa": "UCUQUER LTDA", "Actividad económica": "Cultivo de productos agrícolas en combinación con la cría de animales (explotación mixta)", "Ubicacion": "O'Higgins, Litueche", "Fecha": "19/08/2020", "Salario": "450.001\n - \n600.000", "Tipo": "Jornada Completa", "Nivel educacional": "", "Experiencia": "4 años", "Tipo de contrato": "Contrato indefinido", "Nivel de Cargo ofrecido": "Otro", "Oferta de tipo práctica profesional": "No"}, {"Titulo": "CAJERO Y CAJERA (2 vacantes)", "Ocupacion": "Cajeros y cajeras", "Vacantes": 2, "Empresa": "Confidencial", "Actividad económica": "Transporte de carga por carretera", "Ubicacion": "Atacama, Copiapó", "Fecha": "19/08/2020", "Salario": "Reservado", "Tipo": "Jornada Completa", "Nivel educacional": "", "Experiencia": "2 años", "Tipo de contrato": "Contrato a plazo Fijo", "Nivel de Cargo ofrecido": "Otro", "Oferta de tipo práctica profesional": "No"}, {"Titulo": "CARNICERO (3 vacantes)", "Ocupacion": "Carniceros y carniceras, pescaderos y pescadoras y afines", "Vacantes": 3, "Empresa": "Confidencial", "Actividad económica": "Transporte de carga por carretera", "Ubicacion": "Atacama, Copiapó", "Fecha": "19/08/2020", "Salario": "301.000\n - \n450.000", "Tipo": "Jornada Completa", "Nivel educacional": "", "Experiencia": "2 años", "Tipo de contrato": "Contrato a plazo Fijo", "Nivel de Cargo ofrecido": "Otro", "Oferta de tipo práctica profesional": "No"}, {"Titulo": "AYUDANTE PRODUCCION  (3 vacantes)", "Ocupacion": "Soldadores y soldadoras oxicortadores y oxicortadoras - Albañiles", "Vacantes": 3, "Empresa": "Petricio Industrial (Santiago) S.A", "Actividad económica": "Fabricación de productos metálicos para uso estructural", "Ubicacion": "Metropolitana, Conchalí", "Fecha": "19/08/2020", "Salario": "301.000\n - \n450.000", "Tipo": "Jornada Completa", "Nivel educacional": "", "Experiencia": "1 años", "Tipo de contrato": "Contrato a plazo Fijo", "Nivel de Cargo ofrecido": "Otro", "Oferta de tipo práctica profesional": "No"}, {"Titulo": "Operario de producción - VII Región (2 vacantes)", "Ocupacion": "Empleados y empleadas de servicios de apoyo a la produccion - Productores y trabajadores agropecuarios calificados cuya produccion se destina al mercado", "Vacantes": 2, "Empresa": "Fundacion Arando Esperanza", "Actividad económica": "Otras actividades profesionales, científicas y técnicas n.c.p.", "Ubicacion": "Maule, Curicó", "Fecha": "19/08/2020", "Salario": "301.000\n - \n450.000", "Tipo": "Jornada Parcial/part time", "Nivel educacional": "", "Experiencia": "1 años", "Tipo de contrato": "Contrato indefinido", "Nivel de Cargo ofrecido": "Operario", "Turnos de trabajo": "Solo mañanas", "Solo tarde": "Grupos de Empleo:", "Oferta de tipo práctica profesional": "No"}, {"Titulo": "Operario de producción - XVI Región (2 vacantes)", "Ocupacion": "Empleados y empleadas de servicios de apoyo a la produccion - Productores y trabajadores agropecuarios calificados cuya produccion se destina al mercado", "Vacantes": 2, "Empresa": "Fundacion Arando Esperanza", "Actividad económica": "Otras actividades profesionales, científicas y técnicas n.c.p.", "Ubicacion": "Ñuble, Chillán", "Fecha": "19/08/2020", "Salario": "301.000\n - \n450.000", "Tipo": "Jornada Parcial/part time", "Nivel educacional": "", "Experiencia": "1 años", "Tipo de contrato": "Contrato indefinido", "Nivel de Cargo ofrecido": "Operario", "Turnos de trabajo": "Solo mañanas", "Solo tarde": "Grupos de Empleo:", "Oferta de tipo práctica profesional": "No"}, {"Titulo": "JORNAL (6 vacantes)", "Ocupacion": "Obreros y obreras de la construccion de edificios", "Vacantes": 6, "Empresa": "Confidencial", "Actividad económica": "Construcción de buques, embarcaciones menores y estructuras flotantes", "Descripción de la Empresa": "La misión de nuestra empresa es prestar servicios en perforaciones, transportes, y arriendo de maquinaria pesada, con la garantía que nuestra empresa consta con la calidad del servicio, con el personal capacitado y con la disponibilidad cien por ciento. Nos perfeccionamos en Perforación de Pozos Pro", "Ubicacion": "Atacama, Copiapó", "Fecha": "19/08/2020", "Salario": "Reservado", "Tipo": "No disponible", "Nivel educacional": "", "Experiencia": "1 años", "Tipo de contrato": "Contrato por obra o faena", "Nivel de Cargo ofrecido": "Otro", "Oferta de tipo práctica profesional": "No"}, {"Titulo": "Operario de producción - VIII Región (2 vacantes)", "Ocupacion": "Empleados y empleadas de servicios de apoyo a la produccion - Productores y trabajadores agropecuarios calificados cuya produccion se destina al mercado", "Vacantes": 2, "Empresa": "Fundacion Arando Esperanza", "Actividad económica": "Otras actividades profesionales, científicas y técnicas n.c.p.", "Ubicacion": "Bío Bío, Los Angeles", "Fecha": "19/08/2020", "Salario": "301.000\n - \n450.000", "Tipo": "Jornada Parcial/part time", "Nivel educacional": "", "Experiencia": "1 años", "Tipo de contrato": "Contrato indefinido", "Nivel de Cargo ofrecido": "Operario", "Turnos de trabajo": "Solo mañanas", "Solo tarde": "Grupos de Empleo:", "Oferta de tipo práctica profesional": "No"}, {"Titulo": "Operario de producción - I Región (2 vacantes)", "Ocupacion": "Empleados y empleadas de servicios de apoyo a la produccion - Productores y trabajadores agropecuarios calificados cuya produccion se destina al mercado", "Vacantes": 2, "Empresa": "Fundacion Arando Esperanza", "Actividad económica": "Otras actividades profesionales, científicas y técnicas n.c.p.", "Ubicacion": "Tarapacá, Iquique", "Fecha": "19/08/2020", "Salario": "301.000\n - \n450.000", "Tipo": "Jornada Parcial/part time", "Nivel educacional": "", "Experiencia": "1 años", "Tipo de contrato": "Contrato indefinido", "Nivel de Cargo ofrecido": "Operario", "Turnos de trabajo": "Solo mañanas", "Solo tarde": "Grupos de Empleo:", "Oferta de tipo práctica profesional": "No"}, {"Titulo": "AYUDANTE DE COCINA (5 vacantes)", "Ocupacion": "Cocineros y cocineras", "Vacantes": 5, "Empresa": "Confidencial", "Actividad económica": "Suministro industrial de comidas por encargo; concesión de servicios de alimentación", "Descripción de la Empresa": "Para Sodexo es una misión. Creemos que la calidad de vida ayuda a mantener a las personas saludables, felices y motivadas a lo largo de su vida. Creemos que ayuda a que las organizaciones sean más eficientes y productivas.", "Ubicacion": "Atacama, Copiapó", "Fecha": "19/08/2020", "Salario": "Reservado", "Tipo": "No disponible", "Nivel educacional": "", "Experiencia": "2 años", "Tipo de contrato": "Contrato a plazo Fijo", "Nivel de Cargo ofrecido": "Otro", "Oferta de tipo práctica profesional": "No"}, {"Titulo": "MAESTROS DE COCINA (5 vacantes)", "Ocupacion": "Cocineros y cocineras", "Vacantes": 5, "Empresa": "Confidencial", "Actividad económica": "Suministro industrial de comidas por encargo; concesión de servicios de alimentación", "Descripción de la Empresa": "Para Sodexo es una misión. Creemos que la calidad de vida ayuda a mantener a las personas saludables, felices y motivadas a lo largo de su vida. Creemos que ayuda a que las organizaciones sean más eficientes y productivas.", "Ubicacion": "Atacama, Copiapó", "Fecha": "19/08/2020", "Salario": "450.001\n - \n600.000", "Tipo": "Jornada Completa", "Nivel educacional": "", "Experiencia": "2 años", "Tipo de contrato": "Contrato por obra o faena", "Nivel de Cargo ofrecido": "Otro", "Oferta de tipo práctica profesional": "No"}, {"Titulo": "Operario de producción - II Región (2 vacantes)", "Ocupacion": "Empleados y empleadas de servicios de apoyo a la produccion - Productores y trabajadores agropecuarios calificados cuya produccion se destina al mercado", "Vacantes": 2, "Empresa": "Fundacion Arando Esperanza", "Actividad económica": "Otras actividades profesionales, científicas y técnicas n.c.p.", "Ubicacion": "Antofagasta, Antofagasta", "Fecha": "19/08/2020", "Salario": "301.000\n - \n450.000", "Tipo": "Jornada Parcial/part time", "Nivel educacional": "", "Experiencia": "1 años", "Tipo de contrato": "Contrato indefinido", "Nivel de Cargo ofrecido": "Operario", "Turnos de trabajo": "Solo mañanas", "Solo tarde": "Grupos de Empleo:", "Oferta de tipo práctica profesional": "No"}, {"Titulo": "OPERARIO PRODUCCION PAINE (10 vacantes)", "Ocupacion": "Operarios de procesamiento de alimentos y afines - Operarios y operarias de maquinaria agricola y forestal motorizada", "Vacantes": 10, "Empresa": "Wenco S.A.", "Actividad económica": "Fabricación de productos de plástico", "Ubicacion": "Metropolitana, Paine", "Fecha": "19/08/2020", "Salario": "450.001\n - \n600.000", "Tipo": "Jornada Completa", "Nivel educacional": "", "Experiencia": "2 años", "Tipo de contrato": "Contrato indefinido", "Nivel de Cargo ofrecido": "Operario", "Oferta de tipo práctica profesional": "No"}, {"Titulo": "Ejecutivo Desarrollo Comercial Puerto Montt (1 vacantes)", "Ocupacion": "Representantes comerciales y tecnicos de ventas", "Vacantes": 1, "Empresa": "Entel", "Actividad económica": "Otras actividades de telecomunicaciones n.c.p.", "Descripción de la Empresa": "Sabemos que quieres cambiar el mundo y transformar con responsabilidad nuestra sociedad. Por eso, en Entel podrás encontrar un espacio de desarrollo, diverso e inclusivo, donde tu propia identidad y talento es bienvenido (Ley 21.015)", "Ubicacion": "Los Lagos, Puerto Montt", "Fecha": "19/08/2020", "Salario": "900.001\n - \n1.050.000", "Tipo": "Jornada Completa", "Nivel educacional": "Educación superior Completa", "Experiencia": "2 años", "Titulación": "Técnico en Comercio Exterior", "Ingeniería Comercial": "Técnico en Administración de Ventas", "Tipo de contrato": "Contrato indefinido", "Nivel de Cargo ofrecido": "Ejecutivo", "Turnos de trabajo": "Solo mañanas", "Solo tarde": "Grupos de Empleo:", "Oferta de tipo práctica profesional": "No"}, {"Titulo": "Software Engineer Manager Mobile (1 vacantes)", "Ocupacion": "Ingenieros e ingenieras civiles - Profesionales de tecnologia de la informacion", "Vacantes": 1, "Empresa": "Marbelma Group", "Actividad económica": "Servicios Generales", "Descripción de la Empresa": "Servicios integrados de relaciones humanas e informática.", "Ubicacion": "Metropolitana, Las Condes", "Fecha": "19/08/2020", "Salario": "1.650.001\n - \n1.800.000", "Tipo": "Jornada Completa", "Nivel educacional": "Educación superior Completa", "Experiencia": "7 años", "Titulación": "Ingeniería Civil Industrial", "Ingeniería Civil en Informática": "Idiomas:", "INGLES": "Tipo de contrato:", "Contrato indefinido": "Nivel de Cargo ofrecido:", "Jefatura": "Oferta de tipo práctica profesional:", "Oferta de tipo práctica profesional": "No"}, {"Titulo": "Denda requiere Technical Lead para Shopify (1 vacantes)", "Ocupacion": "Ingenieros no clasificados - Profesionales de tecnologia de la informacion", "Vacantes": 1, "Empresa": "Marbelma Group", "Actividad económica": "Servicios Generales", "Descripción de la Empresa": "Servicios integrados de relaciones humanas e informática.", "Ubicacion": "Metropolitana, Vitacura", "Fecha": "19/08/2020", "Salario": "1.200.001\n - \n1.350.000", "Tipo": "Jornada Completa", "Nivel educacional": "Educación superior Completa", "Experiencia": "5 años", "Titulación": "Ingeniería en Informática", "Ingeniería Civil en Informática": "Ingeniería Civil en Computación e Informática", "Ingeniería de Ejecución en Computación e Informática": "Ingeniería en Computación e Informática", "Idiomas": "INGLES: (Lectura: Alto,\n                                                Escritura:\n                                                Alto, Hablado: Alto)", "Tipo de contrato": "Contrato indefinido", "Nivel de Cargo ofrecido": "Profesional", "Oferta de tipo práctica profesional": "No"}, {"Titulo": "Conductor (4 vacantes)", "Ocupacion": "Conductores y conductoras de automoviles taxis, camionetas y motocicletas", "Vacantes": 4, "Empresa": "ctr seleccion", "Actividad económica": "Servicios Generales", "Descripción de la Empresa": "Somos una empresa dedicada a la selección y contratación de personal en todo el país para nuestros clientes del retail", "Ubicacion": "Tarapacá, Iquique", "Fecha": "19/08/2020", "Salario": "450.001\n - \n600.000", "Tipo": "Jornada Completa", "Nivel educacional": "", "Experiencia": "1 años", "Licencias de conducir": "CLASE B - Vehículos motorizados de tres o cuatro ruedas para transporte particular (automóviles, camionetas, furgones, furgonetas, etcétera).", "Tipo de contrato": "Contrato indefinido", "Nivel de Cargo ofrecido": "Otro", "Oferta de tipo práctica profesional": "No"}, {"Titulo": "Operador de Grúa Horquilla (1 vacantes)", "Ocupacion": "Otras ocupaciones", "Vacantes": 1, "Empresa": "Carozzi", "Actividad económica": "Elaboración de macarrones, fideos, alcuzcuz y productos farináceos similares", "Ubicacion": "La Araucanía, Victoria", "Fecha": "19/08/2020", "Salario": "Reservado", "Tipo": "Jornada Completa", "Nivel educacional": "", "Experiencia": "1 años", "Tipo de contrato": "Contrato a plazo Fijo", "Nivel de Cargo ofrecido": "Otro", "Oferta de tipo práctica profesional": "No"}, {"Titulo": "Se busca Conductor/a licencia A4 para empresa de reparto (2 vacantes)", "Ocupacion": "Conductores y conductoras de camiones pesados - Operarios y operarias de maquinas de movimiento de tierras y afines", "Vacantes": 2, "Empresa": "SOCIEDAD DE TRANSPORTES ECHEVERRIA HERMANOS LTDA", "Actividad económica": "Transporte de carga por carretera", "Ubicacion": "Bío Bío, Los Angeles", "Fecha": "19/08/2020", "Salario": "600.001\n - \n750.000", "Tipo": "Jornada Completa", "Nivel educacional": "", "Experiencia": "3 años", "Licencias de conducir": "CLASE A4 - Transporte de carga cuyo peso bruto sea superior a 3.500 kilogramos.", "Tipo de contrato": "Contrato indefinido", "Nivel de Cargo ofrecido": "Otro", "Oferta de tipo práctica profesional": "No"}, {"Titulo": "Analista de sistemas manejo servidores, sistemas operativos,  migraciones y paso a producción (2 vacantes)", "Ocupacion": "Ingenieros e ingenieras electronicas y de telecomunicaciones - Ingenieros no clasificados", "Vacantes": 2, "Empresa": "Xinergia Laboral Servicios Generales", "Actividad económica": "Otras actividades de servicios de apoyo a las empresas n.c.p.", "Ubicacion": "Metropolitana, Santiago", "Fecha": "19/08/2020", "Salario": "Reservado", "Tipo": "Jornada Completa", "Nivel educacional": "Educación superior Completa", "Experiencia": "1 años", "Titulación": "Ingeniería en Telecomunicaciones", "Técnico en Análisis de Sistemas": "Tipo de contrato:", "Contrato a plazo Fijo": "Nivel de Cargo ofrecido:", "Profesional": "Turnos de trabajo:", "Trabajo turno nocturno": "Trabajo turno sab/dom/fest", "Solo mañanas": "Solo tarde", "Oferta de tipo práctica profesional": "No"}, {"Titulo": "1006 - Ejecutivo/a de Atención al Cliente - Sucursal Chillan (Reemplazo) (1 vacantes)", "Ocupacion": "Empleados y empleadas de servicio al cliente, ventanillas etc. - Empleados de servicios de informacion al cliente", "Vacantes": 1, "Empresa": "Caja Los Héroes", "Descripción de la Empresa": "Caja de compensación Los Héroes empresa sin fines de lucro.", "Ubicacion": "Ñuble, Chillán", "Fecha": "19/08/2020", "Salario": "301.000\n - \n450.000", "Tipo": "Jornada Completa", "Nivel educacional": "Educación media completa", "Experiencia": "1 años", "Tipo educación media": "Educación Científico Humanista", "Educación Técnico Profesional": "Tipo de contrato:", "Contrato a plazo Fijo": "Nivel de Cargo ofrecido:", "Administrativo": "Oferta de tipo práctica profesional:", "Oferta de tipo práctica profesional": "No"}, {"Titulo": "OPERARIOS (AS) DE BODEGA - OFERTA DE OMIL LAMPA (10 vacantes)", "Ocupacion": "Empleados y empleadas de control de abastecimientos e inventario", "Vacantes": 10, "Empresa": "Xinergia", "Actividad económica": "Actividades de asociaciones profesionales", "Ubicacion": "Metropolitana, Lampa", "Fecha": "19/08/2020", "Salario": "301.000\n - \n450.000", "Tipo": "Jornada Completa", "Nivel educacional": "Educación media completa", "Experiencia": "1 años", "Tipo educación media": "Educación Científico Humanista", "Tipo de contrato": "Contrato a plazo Fijo", "Nivel de Cargo ofrecido": "Otro", "Oferta de tipo práctica profesional": "No"}, {"Titulo": "CUIDADO DE PARCELA (2 vacantes)", "Ocupacion": "Guardias porteros y porteras", "Vacantes": 2, "Empresa": "Confidencial", "Actividad económica": "Cultivo de otras plantas perennes", "Ubicacion": "O'Higgins, Rengo", "Fecha": "19/08/2020", "Salario": "301.000\n - \n450.000", "Tipo": "Jornada Completa", "Nivel educacional": "", "Experiencia": "1 años", "Licencias de conducir": "CLASE B - Vehículos motorizados de tres o cuatro ruedas para transporte particular (automóviles, camionetas, furgones, furgonetas, etcétera).", "Tipo de contrato": "Contrato a plazo Fijo", "Nivel de Cargo ofrecido": "Auxiliar", "Oferta de tipo práctica profesional": "No"}, {"Titulo": "MOTORISTA COMIDA RÁPIDA - OMIL LAMPA (2 vacantes)", "Ocupacion": "Conductores y conductoras de automoviles taxis, camionetas y motocicletas", "Vacantes": 2, "Empresa": "ADMINISTRADORA DE FRANQUICIAS RENACIMIENTO SPA", "Actividad económica": "Otra", "Ubicacion": "Metropolitana, Lampa", "Fecha": "19/08/2020", "Salario": "301.000\n - \n450.000", "Tipo": "Jornada Completa", "Nivel educacional": "", "Experiencia": "1 años", "Licencias de conducir": "CLASE C - Para vehículos de dos o tres ruedas con motor fijo o agregado (motocicletas, motonetas).", "Tipo de contrato": "Contrato a plazo Fijo", "Nivel de Cargo ofrecido": "Otro", "Oferta de tipo práctica profesional": "No"}, {"Titulo": "CHOFER REPARTIDOR - OMIL LAMPA  (1 vacantes)", "Ocupacion": "Conductores y conductoras de camiones pesados", "Vacantes": 1, "Empresa": "RyC limitada", "Actividad económica": "Venta al por menor de combustibles para vehículos automotores en comercios especializados", "Ubicacion": "Metropolitana, Lampa", "Fecha": "19/08/2020", "Salario": "301.000\n - \n450.000", "Tipo": "Jornada Completa", "Nivel educacional": "", "Experiencia": "No requerida", "Tipo de contrato": "Contrato a plazo Fijo", "Nivel de Cargo ofrecido": "Otro", "Oferta de tipo práctica profesional": "No"}, {"Titulo": "VENDEDOR PLANES TELEFONIA MÓVIL (10 vacantes)", "Ocupacion": "Vendedores y vendedoras a domicilio y por telefono", "Vacantes": 10, "Empresa": "SPM", "Actividad económica": "Venta al por menor por correo, por internet y vía telefónica", "Descripción de la Empresa": "Importante empresa del área de Call Center", "Ubicacion": "Metropolitana, Santiago", "Fecha": "19/08/2020", "Salario": "Reservado", "Tipo": "Sin limitación horaria", "Nivel educacional": "Educación media completa", "Experiencia": "No requerida", "Tipo educación media": "Educación Científico Humanista", "Tipo de contrato": "Honorarios", "Nivel de Cargo ofrecido": "Otro", "Turnos de trabajo": "Oferta de tipo práctica profesional:", "Oferta de tipo práctica profesional": "No"}, {"Titulo": "Conductor de camión grúa doble (1 vacantes)", "Ocupacion": "Conductores y conductoras de camiones pesados", "Vacantes": 1, "Empresa": "Gruas Baeza", "Actividad económica": "Actividades de servicios vinculadas al transporte terrestre n.c.p.", "Ubicacion": "Metropolitana, La Granja", "Fecha": "19/08/2020", "Salario": "450.001\n - \n600.000", "Tipo": "Jornada Completa", "Nivel educacional": "Educación media completa", "Experiencia": "1 años", "Tipo educación media": "Educación Técnico Profesional", "Educación Científico Humanista": "Licencias de conducir:", "CLASE A4 - Transporte de carga cuyo peso bruto sea superior a 3.500 kilogramos.": "Tipo de contrato:", "Contrato indefinido": "Nivel de Cargo ofrecido:", "Profesional": "Oferta de tipo práctica profesional:", "Oferta de tipo práctica profesional": "No"}, {"Titulo": "JUNIOR ADMINISTRATIVO (1 vacantes)", "Ocupacion": "Junior y estafeta - Otras ocupaciones", "Vacantes": 1, "Empresa": "Licores Mitjans S.A.", "Actividad económica": "Destilación, rectificación y mezclas de bebidas alcohólicas; excepto pisco", "Ubicacion": "Metropolitana, Macúl", "Fecha": "19/08/2020", "Salario": "301.000\n - \n450.000", "Tipo": "Jornada Completa", "Nivel educacional": "Educación media completa", "Experiencia": "2 años", "Tipo educación media": "Educación Técnico Profesional", "Tipo de contrato": "Contrato a plazo Fijo", "Nivel de Cargo ofrecido": "Auxiliar", "Oferta de tipo práctica profesional": "No"}, {"Titulo": "MENSAJEROS(AS) Y REPARTIDORES(AS) (15 vacantes)", "Ocupacion": "Mensajeros y mensajeras  Repartidores y repartidoras", "Vacantes": 15, "Empresa": "chilepost", "Actividad económica": "Actividades de servicios vinculadas al transporte terrestre n.c.p.", "Ubicacion": "Metropolitana, Santiago", "Fecha": "19/08/2020", "Salario": "301.000\n - \n450.000", "Tipo": "Jornada Completa", "Nivel educacional": "", "Experiencia": "1 años", "Tipo de contrato": "", "Nivel de Cargo ofrecido": "Otro", "Turnos de trabajo": "Oferta de tipo práctica profesional:", "Oferta de tipo práctica profesional": "No"}, {"Titulo": "VENDEDOR/A (1 vacantes)", "Ocupacion": "Vendedores y vendedoras de tiendas y almacenes", "Vacantes": 1, "Empresa": "Omil Nueva Imperial", "Actividad económica": "Actividades de la administración pública en general", "Ubicacion": "La Araucanía, Nueva Imperial", "Fecha": "19/08/2020", "Salario": "Reservado", "Tipo": "Jornada Completa", "Nivel educacional": "", "Experiencia": "1 años", "Tipo de contrato": "Contrato a plazo Fijo", "Nivel de Cargo ofrecido": "Operario", "Oferta de tipo práctica profesional": "No"}, {"Titulo": "OPERARIA LAVANDERIA (1 vacantes)", "Ocupacion": "Lavanderos lavanderas y planchadores manuales - Operadores y operadoras de maquinas de lavanderia blanqueo teñido y tintura", "Vacantes": 1, "Empresa": "LAVACENTER EXPRESS S..A", "Actividad económica": "Lavado y limpieza, incluida la limpieza en seco, de productos textiles y de piel", "Ubicacion": "Metropolitana, Quilicura", "Fecha": "19/08/2020", "Salario": "301.000\n - \n450.000", "Tipo": "Jornada Completa", "Nivel educacional": "", "Experiencia": "No requerida", "Tipo de contrato": "Contrato a plazo Fijo", "Nivel de Cargo ofrecido": "Operario", "Oferta de tipo práctica profesional": "No"}, {"Titulo": "Auxiliar de servicios generales - RM (2 vacantes)", "Ocupacion": "Personal domestico - Limpiadores y limpiadoras de establecimientos", "Vacantes": 2, "Empresa": "Fundacion Arando Esperanza", "Actividad económica": "Otras actividades profesionales, científicas y técnicas n.c.p.", "Ubicacion": "Metropolitana, Santiago", "Fecha": "19/08/2020", "Salario": "301.000\n - \n450.000", "Tipo": "Jornada Parcial/part time", "Nivel educacional": "", "Experiencia": "1 años", "Tipo de contrato": "Contrato indefinido", "Nivel de Cargo ofrecido": "Auxiliar", "Turnos de trabajo": "Solo mañanas", "Solo tarde": "Grupos de Empleo:", "Oferta de tipo práctica profesional": "No"}, {"Titulo": "Bodeguero (4 vacantes)", "Ocupacion": "Profesionales de nivel medio de servicios administrativos y afines", "Vacantes": 4, "Empresa": "Constructora Excon S.A.", "Actividad económica": "Preparación del terreno", "Ubicacion": "Metropolitana, Colina", "Fecha": "19/08/2020", "Salario": "600.001\n - \n750.000", "Tipo": "Jornada Completa", "Nivel educacional": "Educación media completa", "Experiencia": "3 años", "Tipo educación media": "Educación Técnico Profesional", "Tipo de contrato": "Contrato por obra o faena", "Nivel de Cargo ofrecido": "Técnico", "Turnos de trabajo": "Oferta de tipo práctica profesional:", "Oferta de tipo práctica profesional": "No"}, {"Titulo": "ayudante de mecánico (2 vacantes)", "Ocupacion": "Mecanicos y mecanicas automotrices", "Vacantes": 2, "Empresa": "Confidencial", "Actividad económica": "Mantenimiento y reparación de motocicletas", "Descripción de la Empresa": "mecánica de motos", "Ubicacion": "Metropolitana, Las Condes", "Fecha": "19/08/2020", "Salario": "301.000\n - \n450.000", "Tipo": "Jornada Completa", "Nivel educacional": "", "Experiencia": "No requerida", "Licencias de conducir": "CLASE B - Vehículos motorizados de tres o cuatro ruedas para transporte particular (automóviles, camionetas, furgones, furgonetas, etcétera).", "Tipo de contrato": "Contrato a plazo Fijo", "Nivel de Cargo ofrecido": "Técnico", "Oferta de tipo práctica profesional": "No"}, {"Titulo": "Supervisor de Seguridad (2 vacantes)", "Ocupacion": "Inspectores de seguridad y salud y control de calidad - Guardias de seguridad", "Vacantes": 2, "Empresa": "Confidencial", "Actividad económica": "Exportación/Importación", "Ubicacion": "Los Lagos, Puerto Montt", "Fecha": "19/08/2020", "Salario": "600.001\n - \n750.000", "Tipo": "Jornada Completa", "Nivel educacional": "Educación media completa", "Experiencia": "2 años", "Tipo educación media": "Educación Científico Humanista", "Tipo de contrato": "Contrato a plazo Fijo", "Nivel de Cargo ofrecido": "Supervisor", "Turnos de trabajo": "Oferta de tipo práctica profesional:", "Oferta de tipo práctica profesional": "No"}, {"Titulo": "Técnico de Telecomunicaciones / Concepción (5 vacantes)", "Ocupacion": "Tecnicos en electronica y telecomunicaciones - Instaladores e instaladoras y reparadores de lineas electricas", "Vacantes": 5, "Empresa": "Confidencial", "Actividad económica": "Terminación y acabado de edificios", "Ubicacion": "Bío Bío, Concepción", "Fecha": "19/08/2020", "Salario": "Reservado", "Tipo": "Jornada Completa", "Nivel educacional": "Educación media completa", "Experiencia": "1 años", "Tipo educación media": "Educación Técnico Profesional", "Capacitaciones": "Relacionado a Telecomunicaciones (deseable)", "Licencias de conducir": "CLASE B - Vehículos motorizados de tres o cuatro ruedas para transporte particular (automóviles, camionetas, furgones, furgonetas, etcétera).", "Tipo de contrato": "Contrato indefinido", "Nivel de Cargo ofrecido": "Técnico", "Turnos de trabajo": "Oferta de tipo práctica profesional:", "Oferta de tipo práctica profesional": "No"}, {"Titulo": "SECRETARIA RECEPCIONISTA - OMIL LAMPA (1 vacantes)", "Ocupacion": "Secretarios y secretarias", "Vacantes": 1, "Empresa": "epothan", "Actividad económica": "Fabricación de otras sustancias químicas básicas n.c.p.", "Ubicacion": "Metropolitana, Lampa", "Fecha": "19/08/2020", "Salario": "301.000\n - \n450.000", "Tipo": "Jornada Completa", "Nivel educacional": "Educación media completa", "Experiencia": "No requerida", "Tipo educación media": "Educación Científico Humanista", "Tipo de contrato": "Contrato a plazo Fijo", "Nivel de Cargo ofrecido": "Otro", "Oferta de tipo práctica profesional": "No"}, {"Titulo": "OPERADOR DE GRÚA HORQUILLA - OMIL LAMPA (1 vacantes)", "Ocupacion": "Operadores y operadoras de maquinas herramientas", "Vacantes": 1, "Empresa": "Delibest Agencia en Chile", "Actividad económica": "Suministro industrial de comidas por encargo; concesión de servicios de alimentación", "Ubicacion": "Metropolitana, Lampa", "Fecha": "19/08/2020", "Salario": "301.000\n - \n450.000", "Tipo": "Jornada Completa", "Nivel educacional": "", "Experiencia": "1 años", "Licencias de conducir": "CLASE D - Maquinaria automotriz: tractores, palas mecánicas y otros.", "Tipo de contrato": "Contrato a plazo Fijo", "Nivel de Cargo ofrecido": "Otro", "Oferta de tipo práctica profesional": "No"}, {"Titulo": "Gestor de Estrategia (1 vacantes)", "Ocupacion": "Analistas de gestión, organización y afines", "Vacantes": 1, "Empresa": "Sebastian Barros Lagos", "Ubicacion": "Metropolitana, Santiago", "Fecha": "19/08/2020", "Salario": "1.050.001\n - \n1.200.000", "Tipo": "Jornada Completa", "Nivel educacional": "", "Experiencia": "3 años", "Tipo de contrato": "Contrato a plazo Fijo", "Nivel de Cargo ofrecido": "Profesional", "Oferta de tipo práctica profesional": "No"}, {"Titulo": "Analista de Cuentas Laborales (1 vacantes)", "Ocupacion": "Contadores y contadoras", "Vacantes": 1, "Empresa": "Sebastian Barros Lagos", "Ubicacion": "Metropolitana, Santiago", "Fecha": "19/08/2020", "Salario": "750.001\n - \n900.000", "Tipo": "Jornada Completa", "Nivel educacional": "", "Experiencia": "2 años", "Tipo de contrato": "Contrato a plazo Fijo", "Nivel de Cargo ofrecido": "Profesional", "Oferta de tipo práctica profesional": "No"}, {"Titulo": "Guardia  Seguridad (40 vacantes)", "Ocupacion": "Guardias porteros y porteras - Guardias de seguridad", "Vacantes": 40, "Empresa": "Municipalidad Puente Alto", "Actividad económica": "Actividades de la administración pública en general", "Ubicacion": "Metropolitana, Santiago", "Fecha": "19/08/2020", "Salario": "301.000\n - \n450.000", "Tipo": "Jornada Completa", "Nivel educacional": "Educación básica completa", "Experiencia": "2 años", "Tipo de contrato": "Contrato indefinido", "Nivel de Cargo ofrecido": "Otro", "Oferta de tipo práctica profesional": "No"}, {"Titulo": "Jornal (10 vacantes)", "Ocupacion": "Obreros y obreras de obras publicas y mantenimiento: carreteras presas y obras similares - Albañiles", "Vacantes": 10, "Empresa": "Confidencial", "Actividad económica": "Actividades de la administración pública en general", "Ubicacion": "Maule, Pelluhue", "Fecha": "19/08/2020", "Salario": "301.000\n - \n450.000", "Tipo": "Jornada Completa", "Nivel educacional": "", "Experiencia": "1 años", "Tipo de contrato": "Contrato por obra o faena", "Nivel de Cargo ofrecido": "Otro", "Grupos de Empleo": "Oferta de tipo práctica profesional:", "Oferta de tipo práctica profesional": "No"}, {"Titulo": "Operador excavadora (1 vacantes)", "Ocupacion": "Operarios y operarias de maquinas de movimiento de tierras y afines - Conductores y conductoras de camiones pesados", "Vacantes": 1, "Empresa": "ARMICASA SPA", "Actividad económica": "Actividades inmobiliarias realizadas a cambio de una retribución o por contrata", "Ubicacion": "Maule, Villa Alegre", "Fecha": "19/08/2020", "Salario": "301.000\n - \n450.000", "Tipo": "Jornada Completa", "Nivel educacional": "", "Experiencia": "5 años", "Capacitaciones": "licencia clase d", "Licencias de conducir": "CLASE D - Maquinaria automotriz: tractores, palas mecánicas y otros.", "Tipo de contrato": "Contrato a plazo Fijo", "Nivel de Cargo ofrecido": "Operario", "Oferta de tipo práctica profesional": "No"}, {"Titulo": "ayudante de mecánico (2 vacantes)", "Ocupacion": "Mecanicos y mecanicas automotrices", "Vacantes": 2, "Empresa": "GS motos Spa", "Actividad económica": "Mantenimiento y reparación de motocicletas", "Descripción de la Empresa": "mecánica de motos", "Ubicacion": "Metropolitana, Las Condes", "Fecha": "19/08/2020", "Salario": "301.000\n - \n450.000", "Tipo": "Jornada Completa", "Nivel educacional": "", "Experiencia": "No requerida", "Licencias de conducir": "CLASE B - Vehículos motorizados de tres o cuatro ruedas para transporte particular (automóviles, camionetas, furgones, furgonetas, etcétera).", "Tipo de contrato": "Contrato a plazo Fijo", "Nivel de Cargo ofrecido": "Técnico", "Oferta de tipo práctica profesional": "No"}, {"Titulo": "Operario Planta de Procesos - QUELLÓN (3 vacantes)", "Ocupacion": "Operarios de procesamiento de alimentos y afines", "Vacantes": 3, "Empresa": "Importante Empresa Salmonera ubicada en Chiloé", "Actividad económica": "Cultivo y crianza de peces marinos", "Ubicacion": "Los Lagos, Quellón", "Fecha": "19/08/2020", "Salario": "450.001\n - \n600.000", "Tipo": "Jornada Completa", "Nivel educacional": "Educación media completa", "Experiencia": "No requerida", "Tipo educación media": "Educación Científico Humanista", "Tipo de contrato": "Contrato indefinido", "Nivel de Cargo ofrecido": "Operario", "Grupos de Empleo": "Oferta de tipo práctica profesional:", "Oferta de tipo práctica profesional": "No"}, {"Titulo": "Bodeguero (2 vacantes)", "Ocupacion": "Empleados y empleadas de control de abastecimientos e inventario", "Vacantes": 2, "Empresa": "OMIL Panguipulli", "Actividad económica": "Actividades de la administración pública en general", "Ubicacion": "Los Ríos, Panguipulli", "Fecha": "19/08/2020", "Salario": "Reservado", "Tipo": "Jornada Completa", "Nivel educacional": "", "Experiencia": "No requerida", "Tipo de contrato": "", "Nivel de Cargo ofrecido": "No disponible", "Oferta de tipo práctica profesional": "No"}, {"Titulo": "ayudante de mecánico (2 vacantes)", "Ocupacion": "Mecanicos y mecanicas automotrices", "Vacantes": 2, "Empresa": "GS motos Spa", "Actividad económica": "Mantenimiento y reparación de motocicletas", "Descripción de la Empresa": "mecánica de motos", "Ubicacion": "Metropolitana, Las Condes", "Fecha": "19/08/2020", "Salario": "301.000\n - \n450.000", "Tipo": "Jornada Completa", "Nivel educacional": "", "Experiencia": "No requerida", "Licencias de conducir": "CLASE B - Vehículos motorizados de tres o cuatro ruedas para transporte particular (automóviles, camionetas, furgones, furgonetas, etcétera).", "Tipo de contrato": "Contrato a plazo Fijo", "Nivel de Cargo ofrecido": "Técnico", "Oferta de tipo práctica profesional": "No"}, {"Titulo": "Asesor/a del hogar puertas adentro (1 vacantes)", "Ocupacion": "Personal domestico", "Vacantes": 1, "Empresa": "Confidencial", "Actividad económica": "Otras actividades de servicios de información n.c.p.", "Ubicacion": "Ñuble, San Carlos", "Fecha": "19/08/2020", "Salario": "450.001\n - \n600.000", "Tipo": "Sin limitación horaria", "Nivel educacional": "", "Experiencia": "1 años", "Tipo de contrato": "Contrato a plazo Fijo", "Nivel de Cargo ofrecido": "Otro", "Turnos de trabajo": "Trabajo turno nocturno", "Solo mañanas": "Solo tarde", "Oferta de tipo práctica profesional": "No"}, {"Titulo": "OPERARIO DE PRODUCCIÓN (10 vacantes)", "Ocupacion": "Empleados y empleadas de servicios de apoyo a la produccion", "Vacantes": 10, "Empresa": "Municipalidad Puente Alto", "Actividad económica": "Actividades de la administración pública en general", "Ubicacion": "Metropolitana, Macúl", "Fecha": "19/08/2020", "Salario": "301.000\n - \n450.000", "Tipo": "Jornada Completa", "Nivel educacional": "Educación media completa", "Experiencia": "No requerida", "Tipo educación media": "Educación Científico Humanista", "Tipo de contrato": "Contrato a plazo Fijo", "Nivel de Cargo ofrecido": "Operario", "Grupos de Empleo": "Oferta de tipo práctica profesional:", "Oferta de tipo práctica profesional": "No"}, {"Titulo": "director del programa PIE  (1 vacantes)", "Ocupacion": "Psicologos y psicologas", "Vacantes": 1, "Empresa": "Omil de Palmilla", "Actividad económica": "Actividades de la administración pública en general", "Ubicacion": "O'Higgins, Santa Cruz", "Fecha": "19/08/2020", "Salario": "600.001\n - \n750.000", "Tipo": "Jornada Completa", "Nivel educacional": "", "Experiencia": "2 años", "Tipo de contrato": "Contrato a plazo Fijo", "Nivel de Cargo ofrecido": "Jefatura", "Oferta de tipo práctica profesional": "No"}, {"Titulo": "ASISTENTE EJECUTIVA (1 vacantes)", "Ocupacion": "Secretarios administrativos - Secretarios y secretarias", "Vacantes": 1, "Empresa": "Empresa Rubro Sanitario", "Actividad económica": "Limpieza general de edificios", "Ubicacion": "Antofagasta, Antofagasta", "Fecha": "19/08/2020", "Salario": "301.000\n - \n450.000", "Tipo": "Jornada Completa", "Nivel educacional": "Educación media completa", "Experiencia": "No requerida", "Tipo educación media": "Educación Técnico Profesional", "Tipo de contrato": "Contrato a plazo Fijo", "Nivel de Cargo ofrecido": "Administrativo", "Oferta de tipo práctica profesional": "No"}, {"Titulo": "Vendedor (1 vacantes)", "Ocupacion": "Vendedores y vendedoras de tiendas y almacenes - Representantes comerciales y tecnicos de ventas", "Vacantes": 1, "Empresa": "Confidencial", "Actividad económica": "Venta al por menor en comercios de vestuario y productos para el hogar (grandes tiendas)", "Descripción de la Empresa": "Decohogar se dedica a la venta  de corte y confección de vestuario como a la venta de botonera.", "Ubicacion": "La Araucanía, Cunco", "Fecha": "19/08/2020", "Salario": "Reservado", "Tipo": "Jornada Completa", "Nivel educacional": "", "Experiencia": "1 años", "Tipo de contrato": "Contrato indefinido", "Nivel de Cargo ofrecido": "Operario", "Oferta de tipo práctica profesional": "No"}, {"Titulo": "Analista de Sistemas para Supermercados La Fama (5 vacantes)", "Ocupacion": "Tecnicos en programacion informatica - Desarrolladores y analistas de sistemas informáticos", "Vacantes": 5, "Empresa": "Confidencial", "Descripción de la Empresa": "Supermercado", "Ubicacion": "O'Higgins, Santa Cruz", "Fecha": "19/08/2020", "Salario": "Reservado", "Tipo": "Jornada Completa", "Nivel educacional": "", "Experiencia": "1 años", "Tipo de contrato": "Contrato a plazo Fijo", "Nivel de Cargo ofrecido": "Profesional", "Oferta de tipo práctica profesional": "No"}, {"Titulo": "TENS - CUIDADORA ADULTO MAYOR (1 vacantes)", "Ocupacion": "Ayudantes de enfermeria a domicilio", "Vacantes": 1, "Empresa": "OMIL DE CHIGUAYANTE", "Actividad económica": "Actividades de la administración pública en general", "Ubicacion": "Bío Bío, Chiguayante", "Fecha": "19/08/2020", "Salario": "Reservado", "Tipo": "Jornada Parcial/part time", "Nivel educacional": "", "Experiencia": "No requerida", "Tipo de contrato": "", "Nivel de Cargo ofrecido": "No disponible", "Turnos de trabajo": "Trabajo turno sab/dom/fest", "Oferta de tipo práctica profesional": "No"}, {"Titulo": "MECÁNICO INDUSTRIAL (3 vacantes)", "Ocupacion": "Mecanicos y mecanicas de maquinas agricolas e industriales", "Vacantes": 3, "Empresa": "OMIL MARIQUINA", "Actividad económica": "Actividades de la administración pública en general", "Ubicacion": "Los Ríos, Mariquina", "Fecha": "19/08/2020", "Salario": "Reservado", "Tipo": "Jornada Completa", "Nivel educacional": "Educación superior Completa", "Experiencia": "1 años", "Titulación": "Técnico en Mecánica Industrial", "Tipo de contrato": "Contrato por obra o faena", "Nivel de Cargo ofrecido": "No disponible", "Oferta de tipo práctica profesional": "No"}, {"Titulo": "ADMINISTRATIVO LOGISTICO - OMIL LAMPA (1 vacantes)", "Ocupacion": "Profesionales de nivel medio de servicios administrativos y afines", "Vacantes": 1, "Empresa": "Colchones Novatex Ltda", "Actividad económica": "Fabricación de aparatos de uso doméstico", "Ubicacion": "Metropolitana, Lampa", "Fecha": "19/08/2020", "Salario": "301.000\n - \n450.000", "Tipo": "Jornada Completa", "Nivel educacional": "", "Experiencia": "2 años", "Tipo de contrato": "Contrato a plazo Fijo", "Nivel de Cargo ofrecido": "Otro", "Oferta de tipo práctica profesional": "No"}, {"Titulo": "ELECTROMECÁNICO (1 vacantes)", "Ocupacion": "Otras ocupaciones", "Vacantes": 1, "Empresa": "OMIL Ilustre Municipalidad de La Cisterna", "Actividad económica": "Actividades de la administración pública en general", "Ubicacion": "Metropolitana, La Cisterna", "Fecha": "19/08/2020", "Salario": "450.001\n - \n600.000", "Tipo": "Jornada Completa", "Nivel educacional": "", "Experiencia": "1 años", "Tipo de contrato": "Contrato indefinido", "Nivel de Cargo ofrecido": "Técnico", "Turnos de trabajo": "Trabajo turno nocturno", "Solo mañanas": "Oferta de tipo práctica profesional:", "Oferta de tipo práctica profesional": "No"}, {"Titulo": "TRABAJADOR AGRÍCOLA (1 vacantes)", "Ocupacion": "Otras ocupaciones", "Vacantes": 1, "Empresa": "OMIL PAINE", "Actividad económica": "Actividades de la administración pública en general", "Ubicacion": "Metropolitana, Paine", "Fecha": "19/08/2020", "Salario": "Reservado", "Tipo": "Jornada Parcial/part time", "Nivel educacional": "", "Experiencia": "No requerida", "Tipo de contrato": "Contrato por obra o faena", "Nivel de Cargo ofrecido": "Otro", "Oferta de tipo práctica profesional": "No"}, {"Titulo": "Operario de Apilador Eléctrico Crown - OMIL LAMPA (10 vacantes)", "Ocupacion": "Operarios y operarias de gruas de aparatos elevadores y afines", "Vacantes": 10, "Empresa": "ADECCO", "Actividad económica": "Otras actividades de servicios de apoyo a las empresas n.c.p.", "Ubicacion": "Metropolitana, Quilicura", "Fecha": "19/08/2020", "Salario": "301.000\n - \n450.000", "Tipo": "Jornada Completa", "Nivel educacional": "", "Experiencia": "2 años", "Tipo de contrato": "Contrato a plazo Fijo", "Nivel de Cargo ofrecido": "Otro", "Oferta de tipo práctica profesional": "No"}, {"Titulo": "NOCHERO (1 vacantes)", "Ocupacion": "Guardias de seguridad", "Vacantes": 1, "Empresa": "Confidencial", "Actividad económica": "Cultivo de otras plantas perennes", "Ubicacion": "O'Higgins, Peralillo", "Fecha": "19/08/2020", "Salario": "Reservado", "Tipo": "Jornada Completa", "Nivel educacional": "", "Experiencia": "1 años", "Tipo de contrato": "Contrato a plazo Fijo", "Nivel de Cargo ofrecido": "Otro", "Turnos de trabajo": "Trabajo turno nocturno", "Oferta de tipo práctica profesional": "No"}, {"Titulo": "Programador  (1 vacantes)", "Ocupacion": "Tecnicos en programacion informatica", "Vacantes": 1, "Empresa": "Ingeniería e Informática Navis SpA", "Actividad económica": "Actividades de consultoría de informática y de gestión de instalaciones informáticas", "Ubicacion": "Metropolitana, Huechuraba", "Fecha": "19/08/2020", "Salario": "450.001\n - \n600.000", "Tipo": "Jornada Completa", "Nivel educacional": "Educación superior Completa", "Experiencia": "2 años", "Titulación": "Técnico en Computación e Informática", "Ingeniería de Ejecución en Computación e Informática": "Ingeniería en Computación e Informática", "Tipo de contrato": "Contrato a plazo Fijo", "Nivel de Cargo ofrecido": "Técnico", "Oferta de tipo práctica profesional": "No"}, {"Titulo": "Administrativo Atención de Publico (1 vacantes)", "Ocupacion": "Asistentes administrativos de registros financieros, de costos y salarios - Profesionales de nivel medio de servicios administrativos y afines", "Vacantes": 1, "Empresa": "Herreros Human Konsulting", "Actividad económica": "Actividades de agencias de empleo", "Descripción de la Empresa": "Herreros Human Konsulting, empresa de servicios en materias de Reclutamiento y Selección para cargos ejecutivos, mandos medios, técnicos y administrativos.\n\nCon vasta experiencia en el mercado de recursos humanos, contamos a nivel nacional con una sólida base de datos de profesionales", "Ubicacion": "Valparaíso, Viña del Mar", "Fecha": "19/08/2020", "Salario": "Reservado", "Tipo": "Jornada Completa", "Nivel educacional": "Educación media completa", "Experiencia": "2 años", "Tipo educación media": "Educación Técnico Profesional", "Tipo de contrato": "Contrato indefinido", "Nivel de Cargo ofrecido": "Administrativo", "Oferta de tipo práctica profesional": "No"}, {"Titulo": "ADMINISTRATIVO DESPACHO FRO (1 vacantes)", "Ocupacion": "Profesionales de nivel medio de servicios administrativos y afines - Secretarios administrativos", "Vacantes": 1, "Empresa": "Confidencial", "Actividad económica": "Otras actividades de servicios de apoyo a las empresas n.c.p.", "Ubicacion": "O'Higgins, Rengo", "Fecha": "19/08/2020", "Salario": "Reservado", "Tipo": "Jornada Completa", "Nivel educacional": "Educación media completa", "Experiencia": "No requerida", "Tipo educación media": "Educación Técnico Profesional", "Tipo de contrato": "Contrato a plazo Fijo", "Nivel de Cargo ofrecido": "Administrativo", "Turnos de trabajo": "Grupos de Empleo:", "Oferta de tipo práctica profesional": "No"}, {"Titulo": "Trabajador casa particular (1 vacantes)", "Ocupacion": "Personal domestico", "Vacantes": 1, "Empresa": "OMIL DE LOS ANGELES", "Actividad económica": "Actividades de la administración pública en general", "Ubicacion": "Bío Bío, Los Angeles", "Fecha": "19/08/2020", "Salario": "301.000\n - \n450.000", "Tipo": "Jornada Completa", "Nivel educacional": "", "Experiencia": "1 años", "Tipo de contrato": "Contrato a plazo Fijo", "Nivel de Cargo ofrecido": "Otro", "Turnos de trabajo": "Oferta de tipo práctica profesional:", "Oferta de tipo práctica profesional": "No"}, {"Titulo": "Yalero  (2 vacantes)", "Ocupacion": "Operarios y operarias de gruas de aparatos elevadores y afines", "Vacantes": 2, "Empresa": "OMIL Panguipulli", "Actividad económica": "Actividades de la administración pública en general", "Ubicacion": "Los Ríos, Panguipulli", "Fecha": "19/08/2020", "Salario": "Reservado", "Tipo": "Jornada Completa", "Nivel educacional": "", "Experiencia": "No requerida", "Licencias de conducir": "CLASE D - Maquinaria automotriz: tractores, palas mecánicas y otros.", "Tipo de contrato": "Contrato a plazo Fijo", "Nivel de Cargo ofrecido": "No disponible", "Oferta de tipo práctica profesional": "No"}, {"Titulo": "Carpinteros/as (15 vacantes)", "Ocupacion": "Carpinteros y carpinteras de armar y de blanco", "Vacantes": 15, "Empresa": "Confidencial", "Actividad económica": "Construcción de edificios para uso residencial", "Ubicacion": "Ñuble, Yungay", "Fecha": "19/08/2020", "Salario": "450.001\n - \n600.000", "Tipo": "Jornada Completa", "Nivel educacional": "", "Experiencia": "1 años", "Tipo de contrato": "Contrato por obra o faena", "Nivel de Cargo ofrecido": "Otro", "Turnos de trabajo": "Solo mañanas", "Solo tarde": "Oferta de tipo práctica profesional:", "Oferta de tipo práctica profesional": "No"}, {"Titulo": "Diseñador web (1 vacantes)", "Ocupacion": "Diseñadores gráficos y multimedia - Otras ocupaciones", "Vacantes": 1, "Empresa": "Grupo en su puerta", "Actividad económica": "Otras actividades de venta al por menor en comercios no especializados n.c.p.", "Descripción de la Empresa": "Nuestra razón de ser son los clientes,\ntanto personas como empresas,\nsolucionando sus necesidades a través de\nuna diversidad de productos y servicios,\npor medio de nuestras marcas.", "Ubicacion": "Metropolitana, Maipú", "Fecha": "19/08/2020", "Salario": "Reservado", "Tipo": "Jornada Completa", "Nivel educacional": "Educación superior Completa", "Experiencia": "1 años", "Titulación": "Técnico en Diseño Gráfico", "Tipo de contrato": "Indiferente", "Nivel de Cargo ofrecido": "Administrativo", "Oferta de tipo práctica profesional": "No"}, {"Titulo": "Operador Lavanderia (2 vacantes)", "Ocupacion": "Lavanderos lavanderas y planchadores manuales", "Vacantes": 2, "Empresa": "Aqua Limpia spa", "Actividad económica": "Lavado y limpieza, incluida la limpieza en seco, de productos textiles y de piel", "Ubicacion": "Maule, Talca", "Fecha": "19/08/2020", "Salario": "301.000\n - \n450.000", "Tipo": "Jornada Parcial/part time", "Nivel educacional": "", "Experiencia": "No requerida", "Tipo de contrato": "Contrato a plazo Fijo", "Nivel de Cargo ofrecido": "Otro", "Turnos de trabajo": "Trabajo turno sab/dom/fest", "Oferta de tipo práctica profesional": "No"}, {"Titulo": "ROMANERO  (1 vacantes)", "Ocupacion": "Otras ocupaciones", "Vacantes": 1, "Empresa": "AGROSILOS", "Actividad económica": "Otros servicios de almacenamiento y depósito n.c.p.", "Ubicacion": "Maule, Linares", "Fecha": "19/08/2020", "Salario": "301.000\n - \n450.000", "Tipo": "Jornada Completa", "Nivel educacional": "Educación superior Completa", "Experiencia": "No requerida", "Titulación": "OTROS", "Tipo de contrato": "Contrato a plazo Fijo", "Nivel de Cargo ofrecido": "Otro", "Oferta de tipo práctica profesional": "No"}, {"Titulo": "GUARDIA  (3 vacantes)", "Ocupacion": "Guardias porteros y porteras", "Vacantes": 3, "Empresa": "Confidencial", "Actividad económica": "Alquiler de otros efectos personales y enseres domésticos (incluye mobiliario para eventos)", "Descripción de la Empresa": "ARRIENDO DE CAJAS PLASTICAS A LA CADENA DE SUMINISTRO", "Ubicacion": "Metropolitana, Quilicura", "Fecha": "19/08/2020", "Salario": "301.000\n - \n450.000", "Tipo": "Jornada Completa", "Nivel educacional": "", "Experiencia": "1 años", "Tipo de contrato": "Contrato a plazo Fijo", "Nivel de Cargo ofrecido": "Operario", "Turnos de trabajo": "Oferta de tipo práctica profesional:", "Oferta de tipo práctica profesional": "No"}, {"Titulo": "EJECTUVIO VENTAS TERRENO  (4 vacantes)", "Ocupacion": "Vendedores y vendedoras a domicilio y por telefono", "Vacantes": 4, "Empresa": "Confidencial", "Actividad económica": "Otras actividades de telecomunicaciones n.c.p.", "Ubicacion": "Maule, Linares", "Fecha": "19/08/2020", "Salario": "301.000\n - \n450.000", "Tipo": "Jornada Completa", "Nivel educacional": "Educación media completa", "Experiencia": "1 años", "Tipo educación media": "Educación Científico Humanista", "Tipo de contrato": "Contrato a plazo Fijo", "Nivel de Cargo ofrecido": "Otro", "Oferta de tipo práctica profesional": "No"}, {"Titulo": "ADMINISTRATIVO (1 vacantes)", "Ocupacion": "Secretarios administrativos", "Vacantes": 1, "Empresa": "Confidencial", "Actividad económica": "Otras actividades de telecomunicaciones n.c.p.", "Ubicacion": "Maule, Linares", "Fecha": "19/08/2020", "Salario": "Menora$301.000", "Tipo": "Jornada Parcial/part time", "Nivel educacional": "Educación media completa", "Experiencia": "No requerida", "Tipo educación media": "Educación Científico Humanista", "Tipo de contrato": "Contrato a plazo Fijo", "Nivel de Cargo ofrecido": "Administrativo", "Oferta de tipo práctica profesional": "No"}, {"Titulo": "VENDEDORA - OMIL COLINA (1 vacantes)", "Ocupacion": "Vendedores y vendedoras de tiendas y almacenes", "Vacantes": 1, "Empresa": "INVERSIONES GASTIN S.A", "Actividad económica": "Fabricación de prendas de vestir de materiales textiles y similares", "Ubicacion": "Metropolitana, Colina", "Fecha": "19/08/2020", "Salario": "301.000\n - \n450.000", "Tipo": "No disponible", "Nivel educacional": "Educación media completa", "Experiencia": "2 años", "Tipo educación media": "Educación Científico Humanista", "Tipo de contrato": "", "Nivel de Cargo ofrecido": "Otro", "Oferta de tipo práctica profesional": "No"}, {"Titulo": "Auxiliar de Aseo Quillota (1 vacantes)", "Ocupacion": "Limpiadores y limpiadoras de establecimientos", "Vacantes": 1, "Empresa": "Zonal Sur Consultores", "Ubicacion": "Valparaíso, Quillota", "Fecha": "19/08/2020", "Salario": "Reservado", "Tipo": "Jornada Completa", "Nivel educacional": "Educación media completa", "Experiencia": "1 años", "Tipo educación media": "Educación Científico Humanista", "Tipo de contrato": "Contrato indefinido", "Nivel de Cargo ofrecido": "Auxiliar", "Turnos de trabajo": "Trabajo turno sab/dom/fest", "Solo mañanas": "Solo tarde", "Oferta de tipo práctica profesional": "No"}, {"Titulo": "CHOFER A4 (5 vacantes)", "Ocupacion": "Conductores y conductoras de camiones pesados - Conductor de autobuses", "Vacantes": 5, "Empresa": "ESTABOY LIMITADA", "Actividad económica": "Transporte de carga por carretera", "Ubicacion": "Metropolitana, Conchalí", "Fecha": "19/08/2020", "Salario": "450.001\n - \n600.000", "Tipo": "Jornada Completa", "Nivel educacional": "", "Experiencia": "2 años", "Tipo de contrato": "Contrato indefinido", "Nivel de Cargo ofrecido": "Operario", "Turnos de trabajo": "Solo mañanas", "Solo tarde": "Oferta de tipo práctica profesional:", "Oferta de tipo práctica profesional": "No"}, {"Titulo": "AYUDANTE DE COCINA PARA LOCAL DE SUSHI (1 vacantes)", "Ocupacion": "Cocineros y cocineras", "Vacantes": 1, "Empresa": "OMIL PARRAL", "Actividad económica": "Enseñanza primaria, secundaria científico humanista y técnico profesional privada", "Ubicacion": "Maule, Parral", "Fecha": "19/08/2020", "Salario": "301.000\n - \n450.000", "Tipo": "Jornada Completa", "Nivel educacional": "", "Experiencia": "1 años", "Tipo de contrato": "Contrato indefinido", "Nivel de Cargo ofrecido": "Otro", "Turnos de trabajo": "Oferta de tipo práctica profesional:", "Oferta de tipo práctica profesional": "No"}, {"Titulo": "VENDEDOR SOAP - OMIL COLINA (9 vacantes)", "Ocupacion": "Vendedores y vendedoras de tiendas y almacenes", "Vacantes": 9, "Empresa": "Ana Maria Cornejo Hofmann", "Actividad económica": "Actividades de agentes y corredores de seguros", "Ubicacion": "Metropolitana, Colina", "Fecha": "19/08/2020", "Salario": "301.000\n - \n450.000", "Tipo": "Jornada Completa", "Nivel educacional": "Educación media completa", "Experiencia": "No requerida", "Tipo educación media": "Educación Científico Humanista", "Capacitaciones": "COMPUTACIÓN NIVEL MEDIO", "Tipo de contrato": "Contrato a plazo Fijo", "Nivel de Cargo ofrecido": "Otro", "Grupos de Empleo": "Oferta de tipo práctica profesional:", "Oferta de tipo práctica profesional": "No"}, {"Titulo": "OPERARIOS PROCESOS PACKING (150 vacantes)", "Ocupacion": "Operarios y operarias de maquinaria agricola y forestal motorizada", "Vacantes": 150, "Empresa": "OMIL PARRAL", "Actividad económica": "Enseñanza primaria, secundaria científico humanista y técnico profesional privada", "Ubicacion": "Maule, Parral", "Fecha": "19/08/2020", "Salario": "Reservado", "Tipo": "Jornada Completa", "Nivel educacional": "", "Experiencia": "1 años", "Tipo de contrato": "Contrato por obra o faena", "Nivel de Cargo ofrecido": "Otro", "Turnos de trabajo": "Trabajo turno nocturno", "Oferta de tipo práctica profesional": "No"}, {"Titulo": "Desarrollador página web (2 vacantes)", "Ocupacion": "Diseñadores gráficos y multimedia - Empleados de servicios de informacion al cliente", "Vacantes": 2, "Empresa": "Confidencial", "Actividad económica": "Actividades de asociaciones profesionales", "Descripción de la Empresa": "Empresa de marketing digital y manejo de redes sociales", "Ubicacion": "Metropolitana, Maipú", "Fecha": "19/08/2020", "Salario": "Reservado", "Tipo": "Jornada Parcial/part time", "Nivel educacional": "Educación superior Completa", "Experiencia": "2 años", "Titulación": "Diseño Gráfico", "Técnico en Comunicación Audiovisual": "Técnico en Producción Gráfica y Multimedia", "Idiomas": "INGLES: (Lectura: Bajo,\n                                                Escritura:\n                                                Bajo, Hablado: Bajo)", "Capacitaciones": "Curso de Wordpress", "Tipo de contrato": "Honorarios", "Nivel de Cargo ofrecido": "Especialista", "Oferta de tipo práctica profesional": "No"}, {"Titulo": "AYUDANTES DE COCINA (2 vacantes)", "Ocupacion": "Cocineros y cocineras", "Vacantes": 2, "Empresa": "Confidencial", "Actividad económica": "Actividades de restaurantes y de servicio móvil de comidas", "Ubicacion": "Atacama, Vallenar", "Fecha": "19/08/2020", "Salario": "301.000\n - \n450.000", "Tipo": "Jornada Completa", "Nivel educacional": "Educación básica completa", "Experiencia": "2 años", "Tipo de contrato": "Contrato a plazo Fijo", "Nivel de Cargo ofrecido": "Auxiliar", "Oferta de tipo práctica profesional": "No"}, {"Titulo": "ADMINISTRATIVO CONTABLE  (2 vacantes)", "Ocupacion": "Asistentes de contabilidad", "Vacantes": 2, "Empresa": "Confidencial", "Actividad económica": "Venta al por menor de combustibles para vehículos automotores en comercios especializados", "Ubicacion": "Atacama, Vallenar", "Fecha": "19/08/2020", "Salario": "301.000\n - \n450.000", "Tipo": "Jornada Completa", "Nivel educacional": "Educación media completa", "Experiencia": "2 años", "Tipo educación media": "Educación Técnico Profesional", "Licencias de conducir": "CLASE B - Vehículos motorizados de tres o cuatro ruedas para transporte particular (automóviles, camionetas, furgones, furgonetas, etcétera).", "Tipo de contrato": "Contrato a plazo Fijo", "Nivel de Cargo ofrecido": "Profesional", "Oferta de tipo práctica profesional": "No"}, {"Titulo": "EJECUTIVO DE COBRANZA (2 vacantes)", "Ocupacion": "Cobradores de deudas - Telefonistas", "Vacantes": 2, "Empresa": "Empresa de Cobranza Previsional", "Actividad económica": "Servicios de asesoramiento y representación jurídica", "Ubicacion": "Valparaíso, Valparaíso", "Fecha": "19/08/2020", "Salario": "301.000\n - \n450.000", "Tipo": "Jornada Completa", "Nivel educacional": "Educación media completa", "Experiencia": "1 años", "Tipo educación media": "Educación Científico Humanista", "Tipo de contrato": "Contrato a plazo Fijo", "Nivel de Cargo ofrecido": "Ejecutivo", "Oferta de tipo práctica profesional": "No"}, {"Titulo": "EJECUTIVA (A) VENTAS CALL CENTER - OMIL COLINA (1 vacantes)", "Ocupacion": "Vendedores y vendedoras a domicilio y por telefono", "Vacantes": 1, "Empresa": "INGENIERIA Y SERVICIOS RECAL LTDA", "Actividad económica": "Fabricación de otros productos elaborados de metal n.c.p.", "Ubicacion": "Metropolitana, Colina", "Fecha": "19/08/2020", "Salario": "600.001\n - \n750.000", "Tipo": "Jornada Completa", "Nivel educacional": "Educación media completa", "Experiencia": "2 años", "Tipo educación media": "Educación Científico Humanista", "Tipo de contrato": "Contrato a plazo Fijo", "Nivel de Cargo ofrecido": "Otro", "Oferta de tipo práctica profesional": "No"}, {"Titulo": "Guardia de Seguridad (1 vacantes)", "Ocupacion": "Guardias de seguridad - Guardias porteros y porteras", "Vacantes": 1, "Empresa": "Confidencial", "Actividad económica": "Consejo de administración de edificios y condominios", "Descripción de la Empresa": "Administracion Condominio Valle del Elqui", "Ubicacion": "Coquimbo, La Serena", "Fecha": "19/08/2020", "Salario": "301.000\n - \n450.000", "Tipo": "Jornada Completa", "Nivel educacional": "Educación media completa", "Experiencia": "No requerida", "Tipo educación media": "Educación Científico Humanista", "Tipo de contrato": "Contrato a plazo Fijo", "Nivel de Cargo ofrecido": "Otro", "Turnos de trabajo": "Oferta de tipo práctica profesional:", "Oferta de tipo práctica profesional": "No"}, {"Titulo": "REEMPLAZO COORDINADORA POST VENTA - OMIL COLINA (1 vacantes)", "Ocupacion": "Profesionales de nivel medio de servicios administrativos y afines", "Vacantes": 1, "Empresa": "INGENIERIA Y SERVICIOS RECAL LTDA", "Actividad económica": "Fabricación de otros productos elaborados de metal n.c.p.", "Ubicacion": "Metropolitana, Colina", "Fecha": "19/08/2020", "Salario": "600.001\n - \n750.000", "Tipo": "Jornada Completa", "Nivel educacional": "Educación superior Completa", "Experiencia": "1 años", "Titulación": "Administración de Empresas e Ing. Asociadas", "Tipo de contrato": "Contrato a plazo Fijo", "Nivel de Cargo ofrecido": "Otro", "Oferta de tipo práctica profesional": "No"}, {"Titulo": "Maestro planchero  (1 vacantes)", "Ocupacion": "Cocineros y cocineras", "Vacantes": 1, "Empresa": "Confidencial", "Actividad económica": "Actividades de restaurantes y de servicio móvil de comidas", "Descripción de la Empresa": "Hamburguesería", "Ubicacion": "Bío Bío, San Pedro de la Paz", "Fecha": "19/08/2020", "Salario": "Reservado", "Tipo": "Jornada Completa", "Nivel educacional": "", "Experiencia": "No requerida", "Tipo de contrato": "", "Nivel de Cargo ofrecido": "Técnico", "Grupos de Empleo": "Oferta de tipo práctica profesional:", "Oferta de tipo práctica profesional": "No"}, {"Titulo": "JORNALES (17 vacantes)", "Ocupacion": "Obreros y obreras de la construccion de edificios - Obreros y obreras de obras publicas y mantenimiento: carreteras presas y obras similares", "Vacantes": 17, "Empresa": "Confidencial", "Actividad económica": "Otras actividades especializadas de construcción", "Descripción de la Empresa": "Ingeniería y servicios profesionales.", "Ubicacion": "La Araucanía, Saavedra", "Fecha": "19/08/2020", "Salario": "Reservado", "Tipo": "Jornada Completa", "Nivel educacional": "", "Experiencia": "1 años", "Tipo de contrato": "Contrato por obra o faena", "Nivel de Cargo ofrecido": "Operario", "Oferta de tipo práctica profesional": "No"}, {"Titulo": "Asistente comercial (1 vacantes)", "Ocupacion": "Empleados y empleadas de servicios de apoyo a la produccion", "Vacantes": 1, "Empresa": "Sport Zone S.A.", "Actividad económica": "Venta al por menor de otros artículos y equipos de deporte n.c.p.", "Ubicacion": "Metropolitana, Las Condes", "Fecha": "19/08/2020", "Salario": "450.001\n - \n600.000", "Tipo": "Jornada Completa", "Nivel educacional": "Educación media completa", "Experiencia": "2 años", "Tipo educación media": "Educación Técnico Profesional", "Idiomas": "INGLES: (Lectura: Alto,\n                                                Escritura:\n                                                Alto, Hablado: Medio)", "Tipo de contrato": "Contrato indefinido", "Nivel de Cargo ofrecido": "Asistente", "Oferta de tipo práctica profesional": "No"}, {"Titulo": "Desarrollador PHP Senior (2 vacantes)", "Ocupacion": "Profesionales de tecnologia de la informacion", "Vacantes": 2, "Empresa": "MGTI", "Actividad económica": "Otras actividades de tecnología de la información y de servicios informáticos", "Descripción de la Empresa": "Consultoría Informática.", "Ubicacion": "Metropolitana, Santiago", "Fecha": "19/08/2020", "Salario": "Reservado", "Tipo": "Jornada Completa", "Nivel educacional": "", "Experiencia": "5 años", "Tipo de contrato": "", "Nivel de Cargo ofrecido": "Profesional", "Oferta de tipo práctica profesional": "No"}, {"Titulo": "Técnico Eléctrico (1 vacantes)", "Ocupacion": "Electricistas", "Vacantes": 1, "Empresa": "OMIL Ilustre Municipalidad de La Cisterna", "Actividad económica": "Actividades de la administración pública en general", "Ubicacion": "Metropolitana, La Cisterna", "Fecha": "19/08/2020", "Salario": "301.000\n - \n450.000", "Tipo": "Jornada Completa", "Nivel educacional": "", "Experiencia": "2 años", "Tipo de contrato": "Contrato a plazo Fijo", "Nivel de Cargo ofrecido": "Técnico", "Oferta de tipo práctica profesional": "No"}, {"Titulo": "Analista de Ciber Seguridad (1 vacantes)", "Ocupacion": "Desarrolladores y analistas de sistemas informáticos - Profesionales de tecnologia de la informacion", "Vacantes": 1, "Empresa": "Confidencial", "Actividad económica": "Procesamiento de datos, hospedaje y actividades conexas", "Descripción de la Empresa": "Empresa, con énfasis en desarrollar sistemas de información y software para mejorar la Gestión en las Empresas, focalizados en Sistemas de Información y Aplicaciones especializadas para la Banca e Instituciones Financieras.", "Ubicacion": "Metropolitana, Santiago", "Fecha": "19/08/2020", "Salario": "750.001\n - \n900.000", "Tipo": "Jornada Completa", "Nivel educacional": "Educación superior Completa", "Experiencia": "3 años", "Titulación": "Técnico en Análisis de Sistemas", "Ingeniería en Computación e Informática": "Tipo de contrato:", "Contrato indefinido": "Nivel de Cargo ofrecido:", "Profesional": "Oferta de tipo práctica profesional:", "Oferta de tipo práctica profesional": "No"}, {"Titulo": "Administrador/a de Sistemas (1 vacantes)", "Ocupacion": "Profesionales en redes de computadores - Tecnicos en programacion informatica", "Vacantes": 1, "Empresa": "Confidencial", "Actividad económica": "Procesamiento de datos, hospedaje y actividades conexas", "Descripción de la Empresa": "Empresa, con énfasis en desarrollar sistemas de información y software para mejorar la Gestión en las Empresas, focalizados en Sistemas de Información y Aplicaciones especializadas para la Banca e Instituciones Financieras.", "Ubicacion": "Metropolitana, Santiago", "Fecha": "19/08/2020", "Salario": "Reservado", "Tipo": "Jornada Completa", "Nivel educacional": "Educación superior Completa", "Experiencia": "3 años", "Titulación": "Técnico en Análisis de Sistemas", "Ingeniería en Computación e Informática": "Tipo de contrato:", "Contrato indefinido": "Nivel de Cargo ofrecido:", "Profesional": "Oferta de tipo práctica profesional:", "Oferta de tipo práctica profesional": "No"}, {"Titulo": "Técnico de Telecomunicaciones / Temuco (5 vacantes)", "Ocupacion": "Tecnicos en electronica y telecomunicaciones - Instaladores e instaladoras y reparadores de lineas electricas", "Vacantes": 5, "Empresa": "Confidencial", "Actividad económica": "Terminación y acabado de edificios", "Ubicacion": "La Araucanía, Temuco", "Fecha": "19/08/2020", "Salario": "Reservado", "Tipo": "Jornada Completa", "Nivel educacional": "Educación media completa", "Experiencia": "1 años", "Tipo educación media": "Educación Técnico Profesional", "Capacitaciones": "Relacionado a Telecomunicaciones (deseable)", "Licencias de conducir": "CLASE B - Vehículos motorizados de tres o cuatro ruedas para transporte particular (automóviles, camionetas, furgones, furgonetas, etcétera).", "Tipo de contrato": "Contrato indefinido", "Nivel de Cargo ofrecido": "Técnico", "Turnos de trabajo": "Oferta de tipo práctica profesional:", "Oferta de tipo práctica profesional": "No"}, {"Titulo": "Desarrollador JAVA Senior (2 vacantes)", "Ocupacion": "Profesionales de tecnologia de la informacion", "Vacantes": 2, "Empresa": "MGTI", "Actividad económica": "Otras actividades de tecnología de la información y de servicios informáticos", "Descripción de la Empresa": "Consultoría Informática.", "Ubicacion": "Metropolitana, Santiago", "Fecha": "19/08/2020", "Salario": "Reservado", "Tipo": "Jornada Completa", "Nivel educacional": "", "Experiencia": "5 años", "Tipo de contrato": "", "Nivel de Cargo ofrecido": "Profesional", "Oferta de tipo práctica profesional": "No"}, {"Titulo": "Vendedor (a) de Carnicería Talcahuano (1 vacantes)", "Ocupacion": "Carniceros y carniceras, pescaderos y pescadoras y afines", "Vacantes": 1, "Empresa": "Zonal Sur Consultores", "Ubicacion": "Bío Bío, Talcahuano", "Fecha": "19/08/2020", "Salario": "Reservado", "Tipo": "Jornada Completa", "Nivel educacional": "Educación media completa", "Experiencia": "1 años", "Tipo educación media": "Educación Científico Humanista", "Tipo de contrato": "Contrato indefinido", "Nivel de Cargo ofrecido": "Especialista", "Turnos de trabajo": "Trabajo turno sab/dom/fest", "Solo mañanas": "Solo tarde", "Oferta de tipo práctica profesional": "No"}, {"Titulo": "CONTADOR/A AUDITOR/A (1 vacantes)", "Ocupacion": "Contadores y contadoras - Asistentes de contabilidad", "Vacantes": 1, "Empresa": "Confidencial", "Ubicacion": "Metropolitana, Ñuñoa", "Fecha": "19/08/2020", "Salario": "450.001\n - \n600.000", "Tipo": "Jornada Completa", "Nivel educacional": "", "Experiencia": "2 años", "Tipo de contrato": "Contrato a plazo Fijo", "Nivel de Cargo ofrecido": "Administrativo", "Oferta de tipo práctica profesional": "No"}, {"Titulo": "Ejecutivo de atencion OMIL (1 vacantes)", "Ocupacion": "Profesionales de las ciencias y de la ingenieria", "Vacantes": 1, "Empresa": "omil  quinta de tilcoco", "Actividad económica": "Actividades de la administración pública en general", "Ubicacion": "O'Higgins, Quinta de Tilcoco", "Fecha": "19/08/2020", "Salario": "750.001\n - \n900.000", "Tipo": "Jornada Completa", "Nivel educacional": "Educación superior Completa", "Experiencia": "No requerida", "Titulación": "Ingeniería Comercial", "Tipo de contrato": "Honorarios", "Nivel de Cargo ofrecido": "Profesional", "Oferta de tipo práctica profesional": "No"}, {"Titulo": "Operador de Planta y  Caldera/ Minera Escondida 7x7 (10 vacantes)", "Ocupacion": "Operarios y operarias de maquinas de movimiento de tierras y afines - Mineros y mineras canteros y canteras", "Vacantes": 10, "Empresa": "Randstad", "Actividad económica": "Otras actividades de dotación de recursos humanos", "Ubicacion": "Antofagasta, Antofagasta", "Fecha": "19/08/2020", "Salario": "Reservado", "Tipo": "Jornada Completa", "Nivel educacional": "Educación media completa", "Experiencia": "1 años", "Tipo educación media": "Educación Técnico Profesional", "Tipo de contrato": "Contrato a plazo Fijo", "Nivel de Cargo ofrecido": "Operario", "Oferta de tipo práctica profesional": "No"}, {"Titulo": "REDEROS (1 vacantes)", "Ocupacion": "Otras ocupaciones", "Vacantes": 1, "Empresa": "OMIL TALCAHUANO", "Actividad económica": "Enseñanza preescolar privada", "Ubicacion": "Bío Bío, Talcahuano", "Fecha": "19/08/2020", "Salario": "301.000\n - \n450.000", "Tipo": "Jornada Completa", "Nivel educacional": "", "Experiencia": "No requerida", "Tipo de contrato": "Contrato por obra o faena", "Nivel de Cargo ofrecido": "Otro", "Turnos de trabajo": "Oferta de tipo práctica profesional:", "Oferta de tipo práctica profesional": "No"}, {"Titulo": "Jornal (9 vacantes)", "Ocupacion": "Obreros y obreras de la construccion de edificios", "Vacantes": 9, "Empresa": "Confidencial", "Actividad económica": "Construcción de proyectos de servicio público", "Ubicacion": "Ñuble, Portezuelo", "Fecha": "19/08/2020", "Salario": "Reservado", "Tipo": "Jornada Completa", "Nivel educacional": "", "Experiencia": "No requerida", "Tipo de contrato": "Contrato por obra o faena", "Nivel de Cargo ofrecido": "Otro", "Oferta de tipo práctica profesional": "No"}, {"Titulo": "Enfermera Reemplazo (3 vacantes)", "Ocupacion": "Personal de enfermeria de nivel superior - Personal de enfermeria de nivel medio", "Vacantes": 3, "Empresa": "Confidencial", "Actividad económica": "Actividades de hospitales y clínicas privadas", "Ubicacion": "Valparaíso, Valparaíso", "Fecha": "19/08/2020", "Salario": "Reservado", "Tipo": "Jornada Completa", "Nivel educacional": "", "Experiencia": "1 años", "Tipo de contrato": "Honorarios", "Nivel de Cargo ofrecido": "Profesional", "Oferta de tipo práctica profesional": "No"}, {"Titulo": "Educadora de Trato Directo (Temuco) (1 vacantes)", "Ocupacion": "Trabajador y trabajadora social - Trabajadores y asistentes sociales de nivel medio", "Vacantes": 1, "Empresa": "ECOLIDER EST", "Actividad económica": "Otras actividades de servicios personales n.c.p.", "Ubicacion": "La Araucanía, Temuco", "Fecha": "19/08/2020", "Salario": "301.000\n - \n450.000", "Tipo": "Jornada Completa", "Nivel educacional": "", "Experiencia": "1 años", "Tipo de contrato": "Contrato indefinido", "Nivel de Cargo ofrecido": "Técnico", "Turnos de trabajo": "Trabajo turno nocturno", "Oferta de tipo práctica profesional": "No"}, {"Titulo": "Lider desarrollo de maquinaria agrícola y nuevas tecnologías (1 vacantes)", "Ocupacion": "Operarios y operarias de maquinaria agricola y forestal motorizada", "Vacantes": 1, "Empresa": "Empresas Iansa", "Ubicacion": "Ñuble, Chillán", "Fecha": "19/08/2020", "Salario": "Reservado", "Tipo": "Jornada Completa", "Nivel educacional": "Educación superior Completa", "Experiencia": "5 años", "Titulación": "Agronomía", "Ingeniería Civil Mecánica": "Tipo de contrato:", "Contrato indefinido": "Nivel de Cargo ofrecido:", "Analista": "Oferta de tipo práctica profesional:", "Oferta de tipo práctica profesional": "No"}, {"Titulo": "JUNIOR (1 vacantes)", "Ocupacion": "Junior y estafeta", "Vacantes": 1, "Empresa": "Empresa del Sector", "Actividad económica": "Venta de partes, piezas y accesorios para vehículos automotores", "Ubicacion": "Metropolitana, Renca", "Fecha": "19/08/2020", "Salario": "301.000\n - \n450.000", "Tipo": "Jornada Completa", "Nivel educacional": "", "Experiencia": "1 años", "Tipo de contrato": "Contrato a plazo Fijo", "Nivel de Cargo ofrecido": "Operario", "Oferta de tipo práctica profesional": "No"}, {"Titulo": "VENDEDOR (1 vacantes)", "Ocupacion": "Vendedores y vendedoras a domicilio y por telefono", "Vacantes": 1, "Empresa": "Empresa del Sector", "Actividad económica": "Venta de partes, piezas y accesorios para vehículos automotores", "Ubicacion": "Metropolitana, Renca", "Fecha": "19/08/2020", "Salario": "450.001\n - \n600.000", "Tipo": "Jornada Completa", "Nivel educacional": "", "Experiencia": "3 años", "Tipo de contrato": "Contrato indefinido", "Nivel de Cargo ofrecido": "Administrativo", "Oferta de tipo práctica profesional": "No"}, {"Titulo": "Coordinador Química de residuos (1 vacantes)", "Ocupacion": "Ingenieros medioambientales", "Vacantes": 1, "Empresa": "Confidencial", "Actividad económica": "Captación, tratamiento y distribución de agua", "Ubicacion": "Metropolitana, Quilicura", "Fecha": "19/08/2020", "Salario": "Reservado", "Tipo": "Jornada Completa", "Nivel educacional": "", "Experiencia": "5 años", "Tipo de contrato": "Contrato indefinido", "Nivel de Cargo ofrecido": "Profesional", "Oferta de tipo práctica profesional": "No"}]